{
    "root": "/home/u37216/transformers-importance-sampling",
    "program": "run_glue.py",
    "git": {
        "remote": "https://github.com/prajjwal1/transformers-importance-sampling",
        "commit": "d2de8c200ef65c52f096050b5a23f94429aa2c7c"
    },
    "email": "prajjwalin@protonmail.com",
    "codePath": "run_glue.py",
    "startedAt": "2020-05-17T14:43:12.975848",
    "host": "s001-n019",
    "username": "u37216",
    "executable": "/glob/intel-python/python3/bin/python",
    "os": "Linux-4.15.18-x86_64-with-debian-buster-sid",
    "python": "3.6.3",
    "cpu_count": 24,
    "args": [
        "--model_name_or_path",
        "albert-base-v1",
        "--task_name",
        "MNLI",
        "--do_train",
        "--do_eval",
        "--data_dir",
        "/home/u37216/data/glue_data/MNLI/",
        "--max_seq_length",
        "128",
        "--per_gpu_train_batch_size",
        "32",
        "--learning_rate",
        "2e-5",
        "--num_train_epochs",
        "3.0",
        "--output_dir",
        "/home/u37216/saved_models/"
    ],
    "state": "killed",
    "jobType": null,
    "mode": "run",
    "project": "transformers-importance-sampling",
    "heartbeatAt": "2020-05-17T14:44:05.418812",
    "exitcode": 255
}
